Workbook

Sheet Resumen
A1: Comercios GUIAR San Rafael
A3: Directorio extraído de guiarsanrafael.com.ar · Búsqueda vacía · Páginas 1 a 183 · Actualizado 24 ago 2026
A5: COMERCIOS | C5: CATEGORÍAS | E5: PÁGINAS | G5: NOMBRES ÚNICOS
A6: =COUNTA(tblComercios[Nombre]) | C6: =COUNTA(tblCategorias[Categoría]) | E6: =MAX(tblComercios[Página]) | G6: =SUMPRODUCT((tblComercios[Nombre]<>"")/COUNTIF(tblComercios[Nombre],tblComercios[Nombre]&""))
A7: Fichas /empresa/ | C7: Clasificación GUIAR | E7: Paginación del buscador | G7: Marcas con sucursales
A9: Top 15 categorías
A10: Categoría | B10: Cantidad
A11: =IF(Categorias!B2="","",Categorias!B2) | B11: =IF(A11="","",Categorias!C2)
A12: =IF(Categorias!B3="","",Categorias!B3) | B12: =IF(A12="","",Categorias!C3)
A13: =IF(Categorias!B4="","",Categorias!B4) | B13: =IF(A13="","",Categorias!C4)
A14: =IF(Categorias!B5="","",Categorias!B5) | B14: =IF(A14="","",Categorias!C5)
A15: =IF(Categorias!B6="","",Categorias!B6) | B15: =IF(A15="","",Categorias!C6)
A16: =IF(Categorias!B7="","",Categorias!B7) | B16: =IF(A16="","",Categorias!C7)
A17: =IF(Categorias!B8="","",Categorias!B8) | B17: =IF(A17="","",Categorias!C8)
A18: =IF(Categorias!B9="","",Categorias!B9) | B18: =IF(A18="","",Categorias!C9)
A19: =IF(Categorias!B10="","",Categorias!B10) | B19: =IF(A19="","",Categorias!C10)
A20: =IF(Categorias!B11="","",Categorias!B11) | B20: =IF(A20="","",Categorias!C11)
A21: =IF(Categorias!B12="","",Categorias!B12) | B21: =IF(A21="","",Categorias!C12)
A22: =IF(Categorias!B13="","",Categorias!B13) | B22: =IF(A22="","",Categorias!C13)
... A25: =IF(Categorias!B16="","",Categorias!B16) | B25: =IF(A25="","",Categorias!C16)
A28: Cómo usarlo: abrí la hoja Comercios y filtrá por categoría, nombre o página. La columna URL abre la ficha original en GUIAR. Los totales de este resumen se calculan con fórmulas sobre las tablas; si agregás o quitás filas, actualizá el rango de la tabla Excel.

Sheet Comercios
A1: N° | B1: Nombre | C1: Categoría | D1: Ubicación | E1: Página | F1: ID GUIAR | G1: URL
A2: 1 | B2: 4 ESTACIONES REGIONALES | C2: Artesanias | D2: Artesanias | E2: 53 | F2: 9269 | G2: https://guiarsanrafael.com.ar/empresa/4-estaciones-regionales/
A3: 2 | B3: A La Flauta | C3: Panaderias | D3: Confiteria | E3: 62 | F3: 8677 | G3: https://guiarsanrafael.com.ar/empresa/a-la-flauta/
A4: 3 | B4: A LO CUBANO Barberia | C4: Barberias peluqueria barberos | D4: Barberias | E4: 43 | F4: 9695 | G4: https://guiarsanrafael.com.ar/empresa/a-lo-cubano-barberia/
A5: 4 | B5: Abbona Barcudi Laboratorio | C5: Bioquimicos laboratorio | D5: Bioquimicos | E5: 43 | F5: 9779 | G5: https://guiarsanrafael.com.ar/empresa/abbona-barcudi-laboratorio/
A6: 5 | B6: ABERTURAS EMILIO | C6: Aberturas | D6: Aberturas | E6: 171 | F6: 4320 | G6: https://guiarsanrafael.com.ar/empresa/aberturas-emilio/
A7: 6 | B7: ABSOLUT FITNESS GIM | C7: Gimnasios gym | D7: Gimnasios | E7: 22 | F7: 11980 | G7: https://guiarsanrafael.com.ar/empresa/absolut-fitness-gim/
A8: 7 | B8: ACEROS DEFER S.A. | C8: Ferreteria industrial | D8: Buloneras | E8: 66 | F8: 8550 | G8: https://guiarsanrafael.com.ar/empresa/aceros-defer-s-a/
A9: 8 | B9: Aconcagua Repuestos | C9: Repuestos del automotor autopartes | D9: Autopartes | E9: 73 | F9: 8430 | G9: https://guiarsanrafael.com.ar/empresa/aconcagua-repuestos/
A10: 9 | B10: ACOSTA Vidrios | C10: Cristaleria vidrios | D10: Cristalerias | E10: 68 | F10: 8489 | G10: https://guiarsanrafael.com.ar/empresa/acosta-vidrios/
A11: 10 | B11: Acumuladores Mario Stilo | C11: Baterias | D11: Baterias | E11: 55 | F11: 9217 | G11: https://guiarsanrafael.com.ar/empresa/acumuladores-mario-stilo/
A12: 11 | B12: ACUÑA Romina | C12: Escribanias escribanos escribanas mandatario mandataria notarios notarias | D12: Escribanas | E12: 87 | F12: 8139 | G12: https://guiarsanrafael.com.ar/empresa/acuna-romina/
A13: 12 | B13: ADDICTIVE GIM | C13: Gimnasios gym | D13: Gimnasios | E13: 162 | F13: 5138 | G13: https://guiarsanrafael.com.ar/empresa/addictive-gtm/
... A1817: 1816 | B1817: ZONAZUL Gomería & Lavadero | C1817: Gomerias neumaticos gomas cubiertas | D1817: Gomeria | E1817: 32 | F1817: 10747 | G1817: https://guiarsanrafael.com.ar/empresa/zonazul-gomeria-lavadero/

Sheet Categorias
A1: # | B1: Categoría | C1: Cantidad | D1: % del total
A2: 1 | B2: Abogados abogadas estudios juridicos | C2: =COUNTIF(tblComercios[Categoría],B2) | D2: =IF(SUM($C$2:$C$285)=0,"",C2/SUM($C$2:$C$285))
A3: 2 | B3: Escribanias escribanos escribanas mandatario mandataria notarios notarias | C3: =COUNTIF(tblComercios[Categoría],B3) | D3: =IF(SUM($C$2:$C$285)=0,"",C3/SUM($C$2:$C$285))
A4: 3 | B4: Odontologia | C4: =COUNTIF(tblComercios[Categoría],B4) | D4: =IF(SUM($C$2:$C$285)=0,"",C4/SUM($C$2:$C$285))
A5: 4 | B5: Farmacias | C5: =COUNTIF(tblComercios[Categoría],B5) | D5: =IF(SUM($C$2:$C$285)=0,"",C5/SUM($C$2:$C$285))
A6: 5 | B6: Kinesiologia y fisioterapia | C6: =COUNTIF(tblComercios[Categoría],B6) | D6: =IF(SUM($C$2:$C$285)=0,"",C6/SUM($C$2:$C$285))
A7: 6 | B7: Casa de comidas rotiseria viandas | C7: =COUNTIF(tblComercios[Categoría],B7) | D7: =IF(SUM($C$2:$C$285)=0,"",C7/SUM($C$2:$C$285))
A8: 7 | B8: Clinica medica | C8: =COUNTIF(tblComercios[Categoría],B8) | D8: =IF(SUM($C$2:$C$285)=0,"",C8/SUM($C$2:$C$285))
A9: 8 | B9: Centro de rehabilitacion | C9: =COUNTIF(tblComercios[Categoría],B9) | D9: =IF(SUM($C$2:$C$285)=0,"",C9/SUM($C$2:$C$285))
A10: 9 | B10: Lubricantes aceites lubricentro | C10: =COUNTIF(tblComercios[Categoría],B10) | D10: =IF(SUM($C$2:$C$285)=0,"",C10/SUM($C$2:$C$285))
A11: 10 | B11: Nutricion nutricionistas | C11: =COUNTIF(tblComercios[Categoría],B11) | D11: =IF(SUM($C$2:$C$285)=0,"",C11/SUM($C$2:$C$285))
A12: 11 | B12: Alimentos balanceados | C12: =COUNTIF(tblComercios[Categoría],B12) | D12: =IF(SUM($C$2:$C$285)=0,"",C12/SUM($C$2:$C$285))
A13: 12 | B13: Centro de estetica | C13: =COUNTIF(tblComercios[Categoría],B13) | D13: =IF(SUM($C$2:$C$285)=0,"",C13/SUM($C$2:$C$285))
... A285: 284 | B285: Vidrierias vidrios cristales cristalerias | C285: =COUNTIF(tblComercios[Categoría],B285) | D285: =IF(SUM($C$2:$C$285)=0,"",C285/SUM($C$2:$C$285))
